django_healthchecks/__init__.py
django_healthchecks/admin.py
django_healthchecks/checker.py
django_healthchecks/contrib.py
django_healthchecks/heartbeats.py
django_healthchecks/models.py
django_healthchecks/urls.py
django_healthchecks/views.py
django_healthchecks/migrations/0001_initial.py
django_healthchecks/migrations/__init__.py
django_healthchecks-1.5.0.dist-info/LICENSE
django_healthchecks-1.5.0.dist-info/METADATA
django_healthchecks-1.5.0.dist-info/WHEEL
django_healthchecks-1.5.0.dist-info/top_level.txt
django_healthchecks-1.5.0.dist-info/RECORD
