Metadata-Version: 2.1
Name: django-healthchecks
Version: 1.5.0
Summary: Simple Django app/framework to publish health checks
Home-page: https://github.com/mvantellingen/django-healthchecks
Author: Michael van Tellingen
Author-email: michaelvantellingen@gmail.com
License: MIT
Platform: UNKNOWN
Classifier: Development Status :: 5 - Production/Stable
Classifier: Environment :: Web Environment
Classifier: Framework :: Django
Classifier: Framework :: Django :: 3.2
Classifier: Framework :: Django :: 4.0
Classifier: License :: OSI Approved :: MIT License
Classifier: Programming Language :: Python
Classifier: Programming Language :: Python :: 3.8
Classifier: Programming Language :: Python :: 3.9
Classifier: Programming Language :: Python :: 3.10
Provides-Extra: docs
Provides-Extra: test
